<?xml version="1.0" encoding="UTF-8"?>
<floor BuildingName="A0094001" FloorName="50055641">
    <Domain name="KTH"/>
    <Scale PixelDistance="1575.38" RealDistance="10"/>
    <space name="A0094001_427" type="LAB">
        <contour>
            <centroid x="1449.83" y="2589"/>
            <linesegment x1="1257" y1="2984" x2="1257" y2="2194.04" type="Wall" target=""/>
            <linesegment x1="1257" y1="2194.04" x2="1337.9" y2="2194.04" type="Wall" target=""/>
            <linesegment x1="1337.9" y1="2194.04" x2="1556.16" y2="2194.04" type="Window" target=""/>
            <linesegment x1="1556.16" y1="2194.04" x2="1642.67" y2="2194.04" type="Wall" target=""/>
            <linesegment x1="1642.67" y1="2194.04" x2="1642.67" y2="2774.72" type="Wall" target=""/>
            <linesegment x1="1642.67" y1="2774.72" x2="1642.67" y2="2897.46" type="Portal" target="A0094001_428"/>
            <linesegment x1="1642.67" y1="2897.46" x2="1642.67" y2="2983.93" type="Wall" target=""/>
            <linesegment x1="1642.67" y1="2983.93" x2="1257" y2="2984" type="Wall" target=""/>
        </contour>
        <portal target="A0094001_428"/>
    </space>
    <space name="A0094001_428" type="RÖNTGEN LAB">
        <contour>
            <centroid x="1855.86" y="2589.92"/>
            <linesegment x1="1661.56" y1="2984.05" x2="1661.56" y2="2899.04" type="Wall" target=""/>
            <linesegment x1="1661.56" y1="2899.04" x2="1661.56" y2="2775.05" type="Portal" target="A0094001_427"/>
            <linesegment x1="1661.56" y1="2775.05" x2="1661.56" y2="2195.45" type="Wall" target=""/>
            <linesegment x1="1661.56" y1="2195.45" x2="1743.08" y2="2195.45" type="Wall" target=""/>
            <linesegment x1="1743.08" y1="2195.45" x2="1964" y2="2195.45" type="Window" target=""/>
            <linesegment x1="1964" y1="2195.45" x2="2050.14" y2="2195.45" type="Wall" target=""/>
            <linesegment x1="2050.14" y1="2195.45" x2="2050.14" y2="2984.47" type="Wall" target=""/>
            <linesegment x1="2050.14" y1="2984.47" x2="1925.87" y2="2984.47" type="Wall" target=""/>
            <linesegment x1="1925.87" y1="2984.47" x2="1786.47" y2="2984.47" type="Portal" target="A0094001_414"/>
            <linesegment x1="1786.47" y1="2984.47" x2="1661.56" y2="2984.05" type="Wall" target=""/>
        </contour>
        <portal target="A0094001_427"/>
        <portal target="A0094001_414"/>
    </space>
    <space name="A0094001_414" type="KORRIDOR">
        <contour>
            <centroid x="3352.29" y="3229.26"/>
            <linesegment x1="1238" y1="3392" x2="1238" y2="3103.97" type="Window" target=""/>
            <linesegment x1="1238" y1="3103.97" x2="1763.33" y2="3103.97" type="Wall" target=""/>
            <linesegment x1="1763.33" y1="3103.97" x2="1763.33" y2="3025.72" type="Wall" target=""/>
            <linesegment x1="1763.33" y1="3025.72" x2="1793.59" y2="3025.72" type="Wall" target=""/>
            <linesegment x1="1793.59" y1="3025.72" x2="1915.31" y2="3025.72" type="Portal" target="A0094001_428"/>
            <linesegment x1="1915.31" y1="3025.72" x2="1935.73" y2="3025.72" type="Wall" target=""/>
            <linesegment x1="1935.73" y1="3025.72" x2="1935.73" y2="3105.48" type="Wall" target=""/>
            <linesegment x1="1935.73" y1="3105.48" x2="2170.13" y2="3105.48" type="Wall" target=""/>
            <linesegment x1="2170.13" y1="3105.48" x2="2170.13" y2="3024.57" type="Wall" target=""/>
            <linesegment x1="2170.13" y1="3024.57" x2="2197.35" y2="3024.57" type="Wall" target=""/>
            <linesegment x1="2197.35" y1="3024.57" x2="2322.12" y2="3024.57" type="Portal" target="A0094001_429"/>
            <linesegment x1="2322.12" y1="3024.57" x2="2343.29" y2="3024.57" type="Wall" target=""/>
            <linesegment x1="2343.29" y1="3024.57" x2="2343.29" y2="3104.73" type="Wall" target=""/>
            <linesegment x1="2343.29" y1="3104.73" x2="2575.43" y2="3104.73" type="Wall" target=""/>
            <linesegment x1="2575.43" y1="3104.73" x2="2575.43" y2="3025.33" type="Wall" target=""/>
            <linesegment x1="2575.43" y1="3025.33" x2="2605.67" y2="3025.33" type="Wall" target=""/>
            <linesegment x1="2605.67" y1="3025.33" x2="2729.57" y2="3025.33" type="Portal" target="A0094001_430"/>
            <linesegment x1="2729.57" y1="3025.33" x2="2750.43" y2="3025.33" type="Wall" target=""/>
            <linesegment x1="2750.43" y1="3025.33" x2="2750.43" y2="3105.22" type="Wall" target=""/>
            <linesegment x1="2750.43" y1="3105.22" x2="2982.61" y2="3105.22" type="Wall" target=""/>
            <linesegment x1="2982.61" y1="3105.22" x2="2982.61" y2="3025.22" type="Wall" target=""/>
            <linesegment x1="2982.61" y1="3025.22" x2="3011.42" y2="3025.22" type="Wall" target=""/>
            <linesegment x1="3011.42" y1="3025.22" x2="3134.38" y2="3025.22" type="Portal" target="A0094001_431"/>
            <linesegment x1="3134.38" y1="3025.22" x2="3156.74" y2="3025.22" type="Wall" target=""/>
            <linesegment x1="3156.74" y1="3025.22" x2="3156.74" y2="3104.13" type="Wall" target=""/>
            <linesegment x1="3156.74" y1="3104.13" x2="3389.5" y2="3104.13" type="Wall" target=""/>
            <linesegment x1="3389.5" y1="3104.13" x2="3389.5" y2="3026.55" type="Wall" target=""/>
            <linesegment x1="3389.5" y1="3026.55" x2="3416.45" y2="3026.55" type="Wall" target=""/>
            <linesegment x1="3416.45" y1="3026.55" x2="3541.74" y2="3026.55" type="Portal" target="A0094001_432"/>
            <linesegment x1="3541.74" y1="3026.55" x2="3563.48" y2="3026.55" type="Wall" target=""/>
            <linesegment x1="3563.48" y1="3026.55" x2="3563.48" y2="3105.22" type="Wall" target=""/>
            <linesegment x1="3563.48" y1="3105.22" x2="3794.78" y2="3105.22" type="Wall" target=""/>
            <linesegment x1="3794.78" y1="3105.22" x2="3794.78" y2="3025.22" type="Wall" target=""/>
            <linesegment x1="3794.78" y1="3025.22" x2="3823.48" y2="3025.22" type="Wall" target=""/>
            <linesegment x1="3823.48" y1="3025.22" x2="3948.08" y2="3025.22" type="Portal" target="A0094001_433"/>
            <linesegment x1="3948.08" y1="3025.22" x2="3968.46" y2="3025.22" type="Wall" target=""/>
            <linesegment x1="3968.46" y1="3025.22" x2="3968.46" y2="3104.37" type="Wall" target=""/>
            <linesegment x1="3968.46" y1="3104.37" x2="4202.14" y2="3104.37" type="Wall" target=""/>
            <linesegment x1="4202.14" y1="3104.37" x2="4202.14" y2="3027.31" type="Wall" target=""/>
            <linesegment x1="4202.14" y1="3027.31" x2="4375.65" y2="3027.31" type="Wall" target=""/>
            <linesegment x1="4375.65" y1="3027.31" x2="4375.65" y2="3103.87" type="Wall" target=""/>
            <linesegment x1="4375.65" y1="3103.87" x2="4607.83" y2="3103.87" type="Wall" target=""/>
            <linesegment x1="4607.83" y1="3103.87" x2="4607.83" y2="3026.31" type="Wall" target=""/>
            <linesegment x1="4607.83" y1="3026.31" x2="4636.17" y2="3026.31" type="Wall" target=""/>
            <linesegment x1="4636.17" y1="3026.31" x2="4760.68" y2="3026.31" type="Portal" target="A0094001_435"/>
            <linesegment x1="4760.68" y1="3026.31" x2="4781.1" y2="3026.31" type="Wall" target=""/>
            <linesegment x1="4781.1" y1="3026.31" x2="4781.1" y2="3104.73" type="Wall" target=""/>
            <linesegment x1="4781.1" y1="3104.73" x2="5014.74" y2="3104.73" type="Wall" target=""/>
            <linesegment x1="5014.74" y1="3104.73" x2="5014.74" y2="3025.33" type="Wall" target=""/>
            <linesegment x1="5014.74" y1="3025.33" x2="5042.72" y2="3025.33" type="Wall" target=""/>
            <linesegment x1="5042.72" y1="3025.33" x2="5167" y2="3025.33" type="Portal" target="A0094001_436"/>
            <linesegment x1="5167" y1="3025.33" x2="5206" y2="3025.33" type="Wall" target=""/>
            <linesegment x1="5206" y1="3025.33" x2="5206" y2="3105" type="Wall" target=""/>
            <linesegment x1="5206" y1="3105" x2="5438.97" y2="3105" type="Wall" target=""/>
            <linesegment x1="5438.97" y1="3105" x2="5438.97" y2="3388.18" type="Portal" target="A0094001_404"/>
            <linesegment x1="5438.97" y1="3388.18" x2="5200.95" y2="3388.18" type="Wall" target=""/>
            <linesegment x1="5200.95" y1="3388.18" x2="5063.53" y2="3388.18" type="Portal" target="A0094001_415"/>
            <linesegment x1="5063.53" y1="3388.18" x2="4388.92" y2="3388.18" type="Wall" target=""/>
            <linesegment x1="4388.92" y1="3388.18" x2="4250.4" y2="3388.18" type="Portal" target="A0094001_417"/>
            <linesegment x1="4250.4" y1="3388.18" x2="3973.25" y2="3388.18" type="Wall" target=""/>
            <linesegment x1="3973.25" y1="3388.18" x2="3836" y2="3388.18" type="Portal" target="A0094001_418"/>
            <linesegment x1="3836" y1="3388.18" x2="3745" y2="3388.18" type="Wall" target=""/>
            <linesegment x1="3745" y1="3388.18" x2="3636.06" y2="3388.18" type="Portal" target="A0094001_419"/>
            <linesegment x1="3636.06" y1="3388.18" x2="3532.83" y2="3388.18" type="Wall" target=""/>
            <linesegment x1="3532.83" y1="3388.18" x2="3409.88" y2="3388.18" type="Portal" target="A0094001_420"/>
            <linesegment x1="3409.88" y1="3388.18" x2="3200.79" y2="3388.18" type="Wall" target=""/>
            <linesegment x1="3200.79" y1="3388.18" x2="2941" y2="3388.18" type="Portal" target="A0094001_TRH2"/>
            <linesegment x1="2941" y1="3388.18" x2="2728" y2="3388.18" type="Wall" target=""/>
            <linesegment x1="2728" y1="3388.18" x2="2605.08" y2="3388.18" type="Portal" target="A0094001_423"/>
            <linesegment x1="2605.08" y1="3388.18" x2="2323" y2="3388.18" type="Wall" target=""/>
            <linesegment x1="2323" y1="3388.18" x2="2200.38" y2="3388.18" type="Portal" target="A0094001_424"/>
            <linesegment x1="2200.38" y1="3388.18" x2="1916.82" y2="3388.18" type="Wall" target=""/>
            <linesegment x1="1916.82" y1="3388.18" x2="1792.85" y2="3388.18" type="Portal" target="A0094001_425"/>
            <linesegment x1="1792.85" y1="3388.18" x2="1511.1" y2="3388.18" type="Wall" target=""/>
            <linesegment x1="1511.1" y1="3388.18" x2="1383" y2="3388.18" type="Portal" target="A0094001_426"/>
            <linesegment x1="1383" y1="3388.18" x2="1238" y2="3392" type="Wall" target=""/>
        </contour>
        <portal target="A0094001_428"/>
        <portal target="A0094001_429"/>
        <portal target="A0094001_430"/>
        <portal target="A0094001_431"/>
        <portal target="A0094001_432"/>
        <portal target="A0094001_433"/>
        <portal target="A0094001_435"/>
        <portal target="A0094001_436"/>
        <portal target="A0094001_415"/>
        <portal target="A0094001_417"/>
        <portal target="A0094001_418"/>
        <portal target="A0094001_419"/>
        <portal target="A0094001_420"/>
        <portal target="A0094001_TRH2"/>
        <portal target="A0094001_423"/>
        <portal target="A0094001_424"/>
        <portal target="A0094001_425"/>
        <portal target="A0094001_426"/>
        <portal target="A0094001_404"/>
    </space>
    <space name="A0094001_429" type="KONTOR">
        <contour>
            <centroid x="2262.2" y="2589.72"/>
            <linesegment x1="2066.89" y1="2982.84" x2="2066.89" y2="2194.96" type="Wall" target=""/>
            <linesegment x1="2066.89" y1="2194.96" x2="2149.79" y2="2194.96" type="Wall" target=""/>
            <linesegment x1="2149.79" y1="2194.96" x2="2370.49" y2="2194.96" type="Window" target=""/>
            <linesegment x1="2370.49" y1="2194.96" x2="2457.4" y2="2194.96" type="Wall" target=""/>
            <linesegment x1="2457.4" y1="2194.96" x2="2457.4" y2="2984.79" type="Wall" target=""/>
            <linesegment x1="2457.4" y1="2984.79" x2="2331.11" y2="2984.79" type="Wall" target=""/>
            <linesegment x1="2331.11" y1="2984.79" x2="2192.67" y2="2984.79" type="Portal" target="A0094001_414"/>
            <linesegment x1="2192.67" y1="2984.79" x2="2066.89" y2="2982.84" type="Wall" target=""/>
        </contour>
        <portal target="A0094001_414"/>
    </space>
    <space name="A0094001_430" type="KONTOR">
        <contour>
            <centroid x="2668.06" y="2589.76"/>
            <linesegment x1="2473.95" y1="2985.05" x2="2473.95" y2="2194.96" type="Wall" target=""/>
            <linesegment x1="2473.95" y1="2194.96" x2="2554.02" y2="2194.96" type="Wall" target=""/>
            <linesegment x1="2554.02" y1="2194.96" x2="2774.15" y2="2194.96" type="Window" target=""/>
            <linesegment x1="2774.15" y1="2194.96" x2="2862.2" y2="2194.96" type="Wall" target=""/>
            <linesegment x1="2862.2" y1="2194.96" x2="2862.2" y2="2984.47" type="Wall" target=""/>
            <linesegment x1="2862.2" y1="2984.47" x2="2738.56" y2="2984.47" type="Wall" target=""/>
            <linesegment x1="2738.56" y1="2984.47" x2="2600.33" y2="2984.47" type="Portal" target="A0094001_414"/>
            <linesegment x1="2600.33" y1="2984.47" x2="2473.95" y2="2985.05" type="Wall" target=""/>
        </contour>
        <portal target="A0094001_414"/>
    </space>
    <space name="A0094001_431" type="KONTOR">
        <contour>
            <centroid x="3074.08" y="2589.43"/>
            <linesegment x1="2881.24" y1="2985.78" x2="2881.24" y2="2195.36" type="Wall" target=""/>
            <linesegment x1="2881.24" y1="2195.36" x2="2958.42" y2="2195.36" type="Wall" target=""/>
            <linesegment x1="2958.42" y1="2195.36" x2="3180.63" y2="2195.36" type="Window" target=""/>
            <linesegment x1="3180.63" y1="2195.36" x2="3267.1" y2="2195.36" type="Wall" target=""/>
            <linesegment x1="3267.1" y1="2195.36" x2="3267.1" y2="2983.06" type="Wall" target=""/>
            <linesegment x1="3267.1" y1="2983.06" x2="3145.62" y2="2983.06" type="Wall" target=""/>
            <linesegment x1="3145.62" y1="2983.06" x2="3005.54" y2="2983.06" type="Portal" target="A0094001_414"/>
            <linesegment x1="3005.54" y1="2983.06" x2="2881.24" y2="2985.78" type="Wall" target=""/>
        </contour>
        <portal target="A0094001_414"/>
    </space>
    <space name="A0094001_432" type="KONTOR">
        <contour>
            <centroid x="3480.21" y="2589.33"/>
            <linesegment x1="3675.8" y1="2983.41" x2="3551.16" y2="2983.41" type="Wall" target=""/>
            <linesegment x1="3551.16" y1="2983.41" x2="3411.19" y2="2983.41" type="Portal" target="A0094001_414"/>
            <linesegment x1="3411.19" y1="2983.41" x2="3284.95" y2="2983.41" type="Wall" target=""/>
            <linesegment x1="3284.95" y1="2983.41" x2="3284.95" y2="2195.04" type="Wall" target=""/>
            <linesegment x1="3284.95" y1="2195.04" x2="3364.39" y2="2195.04" type="Wall" target=""/>
            <linesegment x1="3364.39" y1="2195.04" x2="3584.64" y2="2195.04" type="Window" target=""/>
            <linesegment x1="3584.64" y1="2195.04" x2="3675.13" y2="2195.04" type="Wall" target=""/>
            <linesegment x1="3675.13" y1="2195.04" x2="3675.8" y2="2983.41" type="Wall" target=""/>
        </contour>
        <portal target="A0094001_414"/>
    </space>
    <space name="A0094001_433" type="PREP.LAB">
        <contour>
            <centroid x="4064.31" y="2599.77"/>
            <linesegment x1="3693.01" y1="2983.74" x2="3693.01" y2="2743.29" type="Wall" target=""/>
            <linesegment x1="3693.01" y1="2743.29" x2="3785.26" y2="2743.29" type="Wall" target=""/>
            <linesegment x1="3785.26" y1="2743.29" x2="3785.26" y2="2351.94" type="Wall" target=""/>
            <linesegment x1="3785.26" y1="2351.94" x2="3693.93" y2="2351.94" type="Wall" target=""/>
            <linesegment x1="3693.93" y1="2351.94" x2="3693.93" y2="2194.13" type="Wall" target=""/>
            <linesegment x1="3693.93" y1="2194.13" x2="3769.54" y2="2194.13" type="Wall" target=""/>
            <linesegment x1="3769.54" y1="2194.13" x2="3987.18" y2="2194.13" type="Window" target=""/>
            <linesegment x1="3987.18" y1="2194.13" x2="3987.18" y2="2587.98" type="Wall" target=""/>
            <linesegment x1="3987.18" y1="2587.98" x2="4106.85" y2="2587.98" type="Wall" target=""/>
            <linesegment x1="4106.85" y1="2587.98" x2="4106.85" y2="2515" type="Wall" target=""/>
            <linesegment x1="4106.85" y1="2515" x2="4177.2" y2="2515" type="Wall" target=""/>
            <linesegment x1="4177.2" y1="2515" x2="4177.2" y2="2194.13" type="Wall" target=""/>
            <linesegment x1="4177.2" y1="2194.13" x2="4392.87" y2="2194.13" type="Window" target=""/>
            <linesegment x1="4392.87" y1="2194.13" x2="4392.87" y2="2664.43" type="Wall" target=""/>
            <linesegment x1="4392.87" y1="2664.43" x2="4487.13" y2="2664.43" type="Wall" target=""/>
            <linesegment x1="4487.13" y1="2664.43" x2="4487.13" y2="2866.22" type="Wall" target=""/>
            <linesegment x1="4487.13" y1="2866.22" x2="4015.03" y2="2866.22" type="Wall" target=""/>
            <linesegment x1="4015.03" y1="2866.22" x2="4015.03" y2="2983.49" type="Wall" target=""/>
            <linesegment x1="4015.03" y1="2983.49" x2="3955.8" y2="2983.49" type="Wall" target=""/>
            <linesegment x1="3955.8" y1="2983.49" x2="3818.74" y2="2983.49" type="Portal" target="A0094001_414"/>
            <linesegment x1="3818.74" y1="2983.49" x2="3693.01" y2="2983.74" type="Wall" target=""/>
        </contour>
        <portal target="A0094001_414"/>
    </space>
    <space name="A0094001_435" type="EL.LYT. LAB">
        <contour>
            <centroid x="4646.16" y="2595.35"/>
            <linesegment x1="4895.27" y1="2983.74" x2="4772.02" y2="2983.74" type="Wall" target=""/>
            <linesegment x1="4772.02" y1="2983.74" x2="4631.38" y2="2983.74" type="Portal" target="A0094001_414"/>
            <linesegment x1="4631.38" y1="2983.74" x2="4504.35" y2="2983.74" type="Wall" target=""/>
            <linesegment x1="4504.35" y1="2983.74" x2="4504.35" y2="2193.47" type="Wall" target=""/>
            <linesegment x1="4504.35" y1="2193.47" x2="4583.55" y2="2193.47" type="Wall" target=""/>
            <linesegment x1="4583.55" y1="2193.47" x2="4766.73" y2="2193.47" type="Window" target=""/>
            <linesegment x1="4766.73" y1="2193.47" x2="4766.73" y2="2382.61" type="Wall" target=""/>
            <linesegment x1="4766.73" y1="2382.61" x2="4798.49" y2="2382.61" type="Wall" target=""/>
            <linesegment x1="4798.49" y1="2382.61" x2="4798.49" y2="2632.14" type="Wall" target=""/>
            <linesegment x1="4798.49" y1="2632.14" x2="4775.8" y2="2632.14" type="Wall" target=""/>
            <linesegment x1="4775.8" y1="2632.14" x2="4775.8" y2="2951.98" type="Wall" target=""/>
            <linesegment x1="4775.8" y1="2951.98" x2="4896.03" y2="2951.98" type="Wall" target=""/>
            <linesegment x1="4896.03" y1="2951.98" x2="4895.27" y2="2983.74" type="Wall" target=""/>
        </contour>
        <portal target="A0094001_414"/>
    </space>
    <space name="A0094001_436" type="KONTOR">
        <contour>
            <centroid x="5099.39" y="2588.44"/>
            <linesegment x1="4912.3" y1="2981.84" x2="4912.3" y2="2194.39" type="Wall" target=""/>
            <linesegment x1="4912.3" y1="2194.39" x2="4986.83" y2="2194.39" type="Wall" target=""/>
            <linesegment x1="4986.83" y1="2194.39" x2="5206.39" y2="2194.39" type="Window" target=""/>
            <linesegment x1="5206.39" y1="2194.39" x2="5286.43" y2="2194.39" type="Wall" target=""/>
            <linesegment x1="5286.43" y1="2194.39" x2="5286.43" y2="2982.63" type="Wall" target=""/>
            <linesegment x1="5286.43" y1="2982.63" x2="5174.53" y2="2982.63" type="Wall" target=""/>
            <linesegment x1="5174.53" y1="2982.63" x2="5036.62" y2="2982.63" type="Portal" target="A0094001_414"/>
            <linesegment x1="5036.62" y1="2982.63" x2="4912.3" y2="2981.84" type="Wall" target=""/>
        </contour>
        <portal target="A0094001_414"/>
    </space>
    <space name="A0094001_415" type="OPT.MIKROSKOPI LAB">
        <contour>
            <centroid x="4916.61" y="3829.45"/>
            <linesegment x1="4546.96" y1="4221.74" x2="4546.96" y2="3435.16" type="Wall" target=""/>
            <linesegment x1="4546.96" y1="3435.16" x2="5066.92" y2="3435.16" type="Wall" target=""/>
            <linesegment x1="5066.92" y1="3435.16" x2="5193.19" y2="3435.16" type="Portal" target="A0094001_414"/>
            <linesegment x1="5193.19" y1="3435.16" x2="5286.2" y2="3435.16" type="Wall" target=""/>
            <linesegment x1="5286.2" y1="3435.16" x2="5286.2" y2="4223.82" type="Wall" target=""/>
            <linesegment x1="5286.2" y1="4223.82" x2="5229.8" y2="4223.82" type="Wall" target=""/>
            <linesegment x1="5229.8" y1="4223.82" x2="5011.04" y2="4223.82" type="Window" target=""/>
            <linesegment x1="5011.04" y1="4223.82" x2="4824.6" y2="4223.82" type="Wall" target=""/>
            <linesegment x1="4824.6" y1="4223.82" x2="4604.35" y2="4223.82" type="Window" target=""/>
            <linesegment x1="4604.35" y1="4223.82" x2="4546.96" y2="4221.74" type="Wall" target=""/>
        </contour>
        <portal target="A0094001_414"/>
    </space>
    <space name="A0094001_417" type="KONTOR">
        <contour>
            <centroid x="4345.24" y="3829.77"/>
            <linesegment x1="4164.08" y1="4222.31" x2="4164.08" y2="3434.5" type="Wall" target=""/>
            <linesegment x1="4164.08" y1="3434.5" x2="4256.83" y2="3434.5" type="Wall" target=""/>
            <linesegment x1="4256.83" y1="3434.5" x2="4379.72" y2="3434.5" type="Portal" target="A0094001_414"/>
            <linesegment x1="4379.72" y1="3434.5" x2="4526.34" y2="3434.5" type="Wall" target=""/>
            <linesegment x1="4526.34" y1="3434.5" x2="4526.34" y2="4225.2" type="Wall" target=""/>
            <linesegment x1="4526.34" y1="4225.2" x2="4420.48" y2="4225.2" type="Wall" target=""/>
            <linesegment x1="4420.48" y1="4225.2" x2="4200.87" y2="4225.2" type="Window" target=""/>
            <linesegment x1="4200.87" y1="4225.2" x2="4164.08" y2="4222.31" type="Wall" target=""/>
        </contour>
        <portal target="A0094001_414"/>
    </space>
    <space name="A0094001_418" type="KONTOR">
        <contour>
            <centroid x="3962.5" y="3828.29"/>
            <linesegment x1="3779.54" y1="4221.53" x2="3779.54" y2="3433.95" type="Wall" target=""/>
            <linesegment x1="3779.54" y1="3433.95" x2="3841.04" y2="3433.95" type="Wall" target=""/>
            <linesegment x1="3841.04" y1="3433.95" x2="3964.98" y2="3433.95" type="Portal" target="A0094001_414"/>
            <linesegment x1="3964.98" y1="3433.95" x2="4145.46" y2="3433.95" type="Wall" target=""/>
            <linesegment x1="4145.46" y1="3433.95" x2="4145.46" y2="4222.66" type="Wall" target=""/>
            <linesegment x1="4145.46" y1="4222.66" x2="4012.8" y2="4222.66" type="Wall" target=""/>
            <linesegment x1="4012.8" y1="4222.66" x2="3792.31" y2="4222.66" type="Window" target=""/>
            <linesegment x1="3792.31" y1="4222.66" x2="3779.54" y2="4221.53" type="Wall" target=""/>
        </contour>
        <portal target="A0094001_414"/>
    </space>
    <space name="A0094001_419" type="DISP">
        <contour>
            <centroid x="3670.56" y="3595.72"/>
            <linesegment x1="3576.32" y1="3752.99" x2="3750.13" y2="3752.99" type="Wall" target=""/>
            <linesegment x1="3750.13" y1="3752.99" x2="3750.13" y2="3412.8" type="Wall" target=""/>
            <linesegment x1="3750.13" y1="3412.8" x2="3742.12" y2="3412.8" type="Wall" target=""/>
            <linesegment x1="3742.12" y1="3412.8" x2="3636.72" y2="3412.8" type="Portal" target="A0094001_414"/>
            <linesegment x1="3636.72" y1="3412.8" x2="3625.54" y2="3412.8" type="Wall" target=""/>
            <linesegment x1="3625.54" y1="3412.8" x2="3625.54" y2="3543.35" type="Wall" target=""/>
            <linesegment x1="3625.54" y1="3543.35" x2="3574.92" y2="3543.35" type="Wall" target=""/>
            <linesegment x1="3574.92" y1="3543.35" x2="3576.32" y2="3752.99" type="Wall" target=""/>
        </contour>
        <portal target="A0094001_414"/>
    </space>
    <space name="A0094001_420" type="KPR">
        <contour>
            <centroid x="3433.6" y="3737.31"/>
            <linesegment x1="3313.91" y1="4040.87" x2="3313.91" y2="3434" type="Wall" target=""/>
            <linesegment x1="3313.91" y1="3434" x2="3410.63" y2="3434" type="Wall" target=""/>
            <linesegment x1="3410.63" y1="3434" x2="3532.55" y2="3434" type="Portal" target="A0094001_414"/>
            <linesegment x1="3532.55" y1="3434" x2="3553.3" y2="3434" type="Wall" target=""/>
            <linesegment x1="3553.3" y1="3434" x2="3553.3" y2="3822.46" type="Wall" target=""/>
            <linesegment x1="3553.3" y1="3822.46" x2="3553.3" y2="3914.29" type="Portal" target="A0094001_421"/>
            <linesegment x1="3553.3" y1="3914.29" x2="3553.3" y2="4040.56" type="Wall" target=""/>
            <linesegment x1="3553.3" y1="4040.56" x2="3516.53" y2="4040.56" type="Wall" target=""/>
            <linesegment x1="3516.53" y1="4040.56" x2="3425.33" y2="4040.56" type="Portal" target="A0094001_422"/>
            <linesegment x1="3425.33" y1="4040.56" x2="3313.91" y2="4040.87" type="Wall" target=""/>
        </contour>
        <portal target="A0094001_414"/>
        <portal target="A0094001_421"/>
        <portal target="A0094001_422"/>
    </space>
    <space name="A0094001_421" type="TOALETT">
        <contour>
            <centroid x="3657.32" y="3908.48"/>
            <linesegment x1="3574.03" y1="4040.01" x2="3574.03" y2="3915.37" type="Wall" target=""/>
            <linesegment x1="3574.03" y1="3915.37" x2="3574.03" y2="3823.51" type="Portal" target="A0094001_420"/>
            <linesegment x1="3574.03" y1="3823.51" x2="3574.03" y2="3776.38" type="Wall" target=""/>
            <linesegment x1="3574.03" y1="3776.38" x2="3740.5" y2="3776.38" type="Wall" target=""/>
            <linesegment x1="3740.5" y1="3776.38" x2="3740.5" y2="4041.15" type="Wall" target=""/>
            <linesegment x1="3740.5" y1="4041.15" x2="3574.03" y2="4040.01" type="Wall" target=""/>
        </contour>
        <portal target="A0094001_420"/>
    </space>
    <space name="A0094001_422" type="TOALETT">
        <contour>
            <centroid x="3527.66" y="4141.86"/>
            <linesegment x1="3314.18" y1="4224.01" x2="3314.18" y2="4060.44" type="Wall" target=""/>
            <linesegment x1="3314.18" y1="4060.44" x2="3423.56" y2="4060.44" type="Wall" target=""/>
            <linesegment x1="3423.56" y1="4060.44" x2="3515.54" y2="4060.44" type="Portal" target="A0094001_420"/>
            <linesegment x1="3515.54" y1="4060.44" x2="3741.25" y2="4060.44" type="Wall" target=""/>
            <linesegment x1="3741.25" y1="4060.44" x2="3741.25" y2="4223.23" type="Wall" target=""/>
            <linesegment x1="3741.25" y1="4223.23" x2="3588.9" y2="4223.23" type="Wall" target=""/>
            <linesegment x1="3588.9" y1="4223.23" x2="3367.05" y2="4223.23" type="Window" target=""/>
            <linesegment x1="3367.05" y1="4223.23" x2="3314.18" y2="4224.01" type="Wall" target=""/>
        </contour>
        <portal target="A0094001_420"/>
    </space>
    <space name="A0094001_TRH2" type="TRAPPA">
        <contour>
            <centroid x="3071.08" y="3811.92"/>
            <linesegment x1="2874" y1="4221.91" x2="2874" y2="3401.36" type="Wall" target=""/>
            <linesegment x1="2874" y1="3401.36" x2="2941.1" y2="3401.36" type="Wall" target=""/>
            <linesegment x1="2941.1" y1="3401.36" x2="3199.53" y2="3401.36" type="Portal" target="A0094001_414"/>
            <linesegment x1="3199.53" y1="3401.36" x2="3268.14" y2="3401.36" type="Wall" target=""/>
            <linesegment x1="3268.14" y1="3401.36" x2="3268.14" y2="4222.52" type="Wall" target=""/>
            <linesegment x1="3268.14" y1="4222.52" x2="3220.71" y2="4222.52" type="Wall" target=""/>
            <linesegment x1="3220.71" y1="4222.52" x2="2921.91" y2="4222.52" type="Window" target=""/>
            <linesegment x1="2921.91" y1="4222.52" x2="2874" y2="4221.91" type="Wall" target=""/>
        </contour>
        <portal target="A0094001_414"/>
    </space>
    <space name="A0094001_423" type="KONTOR">
        <contour>
            <centroid x="2653.31" y="3818.08"/>
            <linesegment x1="2474.1" y1="4224.57" x2="2474.1" y2="3411.5" type="Wall" target=""/>
            <linesegment x1="2474.1" y1="3411.5" x2="2605.21" y2="3411.5" type="Wall" target=""/>
            <linesegment x1="2605.21" y1="3411.5" x2="2728.17" y2="3411.5" type="Portal" target="A0094001_414"/>
            <linesegment x1="2728.17" y1="3411.5" x2="2832.51" y2="3411.5" type="Wall" target=""/>
            <linesegment x1="2832.51" y1="3411.5" x2="2832.51" y2="4224.68" type="Wall" target=""/>
            <linesegment x1="2832.51" y1="4224.68" x2="2777.01" y2="4224.68" type="Wall" target=""/>
            <linesegment x1="2777.01" y1="4224.68" x2="2555.92" y2="4224.68" type="Window" target=""/>
            <linesegment x1="2555.92" y1="4224.68" x2="2474.1" y2="4224.57" type="Wall" target=""/>
        </contour>
        <portal target="A0094001_414"/>
    </space>
    <space name="A0094001_424" type="KONTOR">
        <contour>
            <centroid x="2262.41" y="3816.8"/>
            <linesegment x1="2068.05" y1="4223.06" x2="2068.05" y2="3409.22" type="Wall" target=""/>
            <linesegment x1="2068.05" y1="3409.22" x2="2196.76" y2="3409.22" type="Wall" target=""/>
            <linesegment x1="2196.76" y1="3409.22" x2="2322.12" y2="3409.22" type="Portal" target="A0094001_414"/>
            <linesegment x1="2322.12" y1="3409.22" x2="2456.71" y2="3409.22" type="Wall" target=""/>
            <linesegment x1="2456.71" y1="3409.22" x2="2456.71" y2="4224.54" type="Wall" target=""/>
            <linesegment x1="2456.71" y1="4224.54" x2="2371" y2="4224.54" type="Wall" target=""/>
            <linesegment x1="2371" y1="4224.54" x2="2152.05" y2="4224.54" type="Window" target=""/>
            <linesegment x1="2152.05" y1="4224.54" x2="2068.05" y2="4223.06" type="Wall" target=""/>
        </contour>
        <portal target="A0094001_414"/>
    </space>
    <space name="A0094001_425" type="KONTOR">
        <contour>
            <centroid x="1855.53" y="3816.82"/>
            <linesegment x1="1662" y1="4223.06" x2="1662" y2="3409.22" type="Wall" target=""/>
            <linesegment x1="1662" y1="3409.22" x2="1793.05" y2="3409.22" type="Wall" target=""/>
            <linesegment x1="1793.05" y1="3409.22" x2="1915" y2="3409.22" type="Portal" target="A0094001_414"/>
            <linesegment x1="1915" y1="3409.22" x2="2049" y2="3409.22" type="Wall" target=""/>
            <linesegment x1="2049" y1="3409.22" x2="2049" y2="4224.57" type="Wall" target=""/>
            <linesegment x1="2049" y1="4224.57" x2="1965.97" y2="4224.57" type="Wall" target=""/>
            <linesegment x1="1965.97" y1="4224.57" x2="1744.99" y2="4224.57" type="Window" target=""/>
            <linesegment x1="1744.99" y1="4224.57" x2="1662" y2="4223.06" type="Wall" target=""/>
        </contour>
        <portal target="A0094001_414"/>
    </space>
    <space name="A0094001_426" type="KONTOR">
        <contour>
            <centroid x="1449.47" y="3815.75"/>
            <linesegment x1="1257.17" y1="4223.23" x2="1257.17" y2="3409.45" type="Wall" target=""/>
            <linesegment x1="1257.17" y1="3409.45" x2="1386.77" y2="3409.45" type="Wall" target=""/>
            <linesegment x1="1386.77" y1="3409.45" x2="1509.66" y2="3409.45" type="Portal" target="A0094001_414"/>
            <linesegment x1="1509.66" y1="3409.45" x2="1641.82" y2="3409.45" type="Wall" target=""/>
            <linesegment x1="1641.82" y1="3409.45" x2="1641.82" y2="4221.91" type="Wall" target=""/>
            <linesegment x1="1641.82" y1="4221.91" x2="1559.63" y2="4221.91" type="Wall" target=""/>
            <linesegment x1="1559.63" y1="4221.91" x2="1336.73" y2="4221.91" type="Window" target=""/>
            <linesegment x1="1336.73" y1="4221.91" x2="1257.17" y2="4223.23" type="Wall" target=""/>
        </contour>
        <portal target="A0094001_414"/>
    </space>
    <space name="A0094001_404" type="KORRIDOR">
        <contour>
            <centroid x="7280.44" y="3234.64"/>
            <linesegment x1="5448.81" y1="3389.35" x2="5448.81" y2="3105.48" type="Portal" target="A0094001_414"/>
            <linesegment x1="5448.81" y1="3105.48" x2="5897.92" y2="3105.48" type="Wall" target=""/>
            <linesegment x1="5897.92" y1="3105.48" x2="6021" y2="3105.48" type="Portal" target="A0094001_438"/>
            <linesegment x1="6021" y1="3105.48" x2="6267" y2="3105.48" type="Wall" target=""/>
            <linesegment x1="6267" y1="3105.48" x2="6267" y2="3029.18" type="Wall" target=""/>
            <linesegment x1="6267" y1="3029.18" x2="6294.4" y2="3029.18" type="Wall" target=""/>
            <linesegment x1="6294.4" y1="3029.18" x2="6419.13" y2="3029.18" type="Portal" target="A0094001_439"/>
            <linesegment x1="6419.13" y1="3029.18" x2="6438.26" y2="3029.18" type="Wall" target=""/>
            <linesegment x1="6438.26" y1="3029.18" x2="6438.26" y2="3108.7" type="Wall" target=""/>
            <linesegment x1="6438.26" y1="3108.7" x2="7077.39" y2="3108.7" type="Wall" target=""/>
            <linesegment x1="7077.39" y1="3108.7" x2="7077.39" y2="3028.7" type="Wall" target=""/>
            <linesegment x1="7077.39" y1="3028.7" x2="7104.35" y2="3028.7" type="Wall" target=""/>
            <linesegment x1="7104.35" y1="3028.7" x2="7228.7" y2="3028.7" type="Portal" target="A0094001_441"/>
            <linesegment x1="7228.7" y1="3028.7" x2="7247.83" y2="3028.7" type="Wall" target=""/>
            <linesegment x1="7247.83" y1="3028.7" x2="7247.83" y2="3108.7" type="Wall" target=""/>
            <linesegment x1="7247.83" y1="3108.7" x2="7484.35" y2="3108.7" type="Wall" target=""/>
            <linesegment x1="7484.35" y1="3108.7" x2="7484.35" y2="3027.83" type="Wall" target=""/>
            <linesegment x1="7484.35" y1="3027.83" x2="7511.3" y2="3027.83" type="Wall" target=""/>
            <linesegment x1="7511.3" y1="3027.83" x2="7635.19" y2="3027.83" type="Portal" target="A0094001_442"/>
            <linesegment x1="7635.19" y1="3027.83" x2="7653.49" y2="3027.83" type="Wall" target=""/>
            <linesegment x1="7653.49" y1="3027.83" x2="7653.49" y2="3106.91" type="Wall" target=""/>
            <linesegment x1="7653.49" y1="3106.91" x2="7889.62" y2="3106.91" type="Wall" target=""/>
            <linesegment x1="7889.62" y1="3106.91" x2="7889.62" y2="3028.01" type="Wall" target=""/>
            <linesegment x1="7889.62" y1="3028.01" x2="7915.92" y2="3028.01" type="Wall" target=""/>
            <linesegment x1="7915.92" y1="3028.01" x2="8039.13" y2="3028.01" type="Portal" target="A0094001_443"/>
            <linesegment x1="8039.13" y1="3028.01" x2="8059.13" y2="3028.01" type="Wall" target=""/>
            <linesegment x1="8059.13" y1="3028.01" x2="8059.13" y2="3109.57" type="Wall" target=""/>
            <linesegment x1="8059.13" y1="3109.57" x2="8294.78" y2="3109.57" type="Wall" target=""/>
            <linesegment x1="8294.78" y1="3109.57" x2="8294.78" y2="3027.2" type="Wall" target=""/>
            <linesegment x1="8294.78" y1="3027.2" x2="8324.16" y2="3027.2" type="Wall" target=""/>
            <linesegment x1="8324.16" y1="3027.2" x2="8445.14" y2="3027.2" type="Portal" target="A0094001_444"/>
            <linesegment x1="8445.14" y1="3027.2" x2="8465.52" y2="3027.2" type="Wall" target=""/>
            <linesegment x1="8465.52" y1="3027.2" x2="8465.52" y2="3109.39" type="Wall" target=""/>
            <linesegment x1="8465.52" y1="3109.39" x2="8700.91" y2="3109.39" type="Wall" target=""/>
            <linesegment x1="8700.91" y1="3109.39" x2="8700.91" y2="3029.18" type="Wall" target=""/>
            <linesegment x1="8700.91" y1="3029.18" x2="8729.19" y2="3029.18" type="Wall" target=""/>
            <linesegment x1="8729.19" y1="3029.18" x2="8850.66" y2="3029.18" type="Portal" target="A0094001_445"/>
            <linesegment x1="8850.66" y1="3029.18" x2="8870.32" y2="3029.18" type="Wall" target=""/>
            <linesegment x1="8870.32" y1="3029.18" x2="8870.32" y2="3107.75" type="Wall" target=""/>
            <linesegment x1="8870.32" y1="3107.75" x2="9051.04" y2="3107.75" type="Wall" target=""/>
            <linesegment x1="9051.04" y1="3107.75" x2="9051.04" y2="3388.28" type="Portal" target="A0094001_TRH1"/>
            <linesegment x1="9051.04" y1="3388.28" x2="8853.69" y2="3388.28" type="Wall" target=""/>
            <linesegment x1="8853.69" y1="3388.28" x2="8729" y2="3388.28" type="Portal" target="A0094001_405"/>
            <linesegment x1="8729" y1="3388.28" x2="8447" y2="3388.28" type="Wall" target=""/>
            <linesegment x1="8447" y1="3388.28" x2="8322" y2="3388.28" type="Portal" target="A0094001_406"/>
            <linesegment x1="8322" y1="3388.28" x2="8041.59" y2="3388.28" type="Wall" target=""/>
            <linesegment x1="8041.59" y1="3388.28" x2="7916.82" y2="3388.28" type="Portal" target="A0094001_407"/>
            <linesegment x1="7916.82" y1="3388.28" x2="7634.78" y2="3388.28" type="Wall" target=""/>
            <linesegment x1="7634.78" y1="3388.28" x2="7511.8" y2="3388.28" type="Portal" target="A0094001_408"/>
            <linesegment x1="7511.8" y1="3388.28" x2="7231.3" y2="3388.28" type="Wall" target=""/>
            <linesegment x1="7231.3" y1="3388.28" x2="7106.96" y2="3388.28" type="Portal" target="A0094001_409"/>
            <linesegment x1="7106.96" y1="3388.28" x2="6824.35" y2="3388.28" type="Wall" target=""/>
            <linesegment x1="6824.35" y1="3388.28" x2="6699.78" y2="3388.28" type="Portal" target="A0094001_410"/>
            <linesegment x1="6699.78" y1="3388.28" x2="6419.66" y2="3388.28" type="Wall" target=""/>
            <linesegment x1="6419.66" y1="3388.28" x2="6297.16" y2="3388.28" type="Portal" target="A0094001_412"/>
            <linesegment x1="6297.16" y1="3388.28" x2="6013.61" y2="3388.28" type="Wall" target=""/>
            <linesegment x1="6013.61" y1="3388.28" x2="5887.77" y2="3388.28" type="Portal" target="A0094001_411"/>
            <linesegment x1="5887.77" y1="3388.28" x2="5448.81" y2="3389.35" type="Wall" target=""/>
        </contour>
        <portal target="A0094001_414"/>
        <portal target="A0094001_438"/>
        <portal target="A0094001_439"/>
        <portal target="A0094001_441"/>
        <portal target="A0094001_442"/>
        <portal target="A0094001_443"/>
        <portal target="A0094001_444"/>
        <portal target="A0094001_445"/>
        <portal target="A0094001_405"/>
        <portal target="A0094001_406"/>
        <portal target="A0094001_407"/>
        <portal target="A0094001_408"/>
        <portal target="A0094001_409"/>
        <portal target="A0094001_410"/>
        <portal target="A0094001_412"/>
        <portal target="A0094001_411"/>
        <portal target="A0094001_TRH1"/>
    </space>
    <space name="A0094001_438" type="HÅRDHETSPROVLAB">
        <contour>
            <centroid x="5750.83" y="2803.22"/>
            <linesegment x1="5357.39" y1="2981.74" x2="5357.39" y2="2626.12" type="Wall" target=""/>
            <linesegment x1="5357.39" y1="2626.12" x2="6145.15" y2="2626.12" type="Wall" target=""/>
            <linesegment x1="6145.15" y1="2626.12" x2="6145.15" y2="2979.6" type="Wall" target=""/>
            <linesegment x1="6145.15" y1="2979.6" x2="6014.97" y2="2979.6" type="Wall" target=""/>
            <linesegment x1="6014.97" y1="2979.6" x2="5890.36" y2="2979.6" type="Portal" target="A0094001_404"/>
            <linesegment x1="5890.36" y1="2979.6" x2="5357.39" y2="2981.74" type="Wall" target=""/>
        </contour>
        <portal target="A0094001_404"/>
    </space>
    <space name="A0094001_439" type="SLIPRUM/LAB">
        <contour>
            <centroid x="6494.34" y="2602.76"/>
            <linesegment x1="6167.5" y1="2979.98" x2="6167.5" y2="2455.95" type="Wall" target=""/>
            <linesegment x1="6167.5" y1="2455.95" x2="6167.5" y2="2331.55" type="Portal" target="A0094001_440"/>
            <linesegment x1="6167.5" y1="2331.55" x2="6167.5" y2="2199.39" type="Wall" target=""/>
            <linesegment x1="6167.5" y1="2199.39" x2="6245.09" y2="2199.39" type="Wall" target=""/>
            <linesegment x1="6245.09" y1="2199.39" x2="6467.33" y2="2199.39" type="Window" target=""/>
            <linesegment x1="6467.33" y1="2199.39" x2="6467.33" y2="2590.61" type="Wall" target=""/>
            <linesegment x1="6467.33" y1="2590.61" x2="6659.21" y2="2590.61" type="Wall" target=""/>
            <linesegment x1="6659.21" y1="2590.61" x2="6659.21" y2="2198.02" type="Wall" target=""/>
            <linesegment x1="6659.21" y1="2198.02" x2="6861.84" y2="2198.02" type="Window" target=""/>
            <linesegment x1="6861.84" y1="2198.02" x2="6861.84" y2="2888.5" type="Wall" target=""/>
            <linesegment x1="6861.84" y1="2888.5" x2="6577.45" y2="2888.5" type="Wall" target=""/>
            <linesegment x1="6577.45" y1="2888.5" x2="6577.45" y2="2981.69" type="Wall" target=""/>
            <linesegment x1="6577.45" y1="2981.69" x2="6427.65" y2="2981.69" type="Wall" target=""/>
            <linesegment x1="6427.65" y1="2981.69" x2="6288.49" y2="2981.69" type="Portal" target="A0094001_404"/>
            <linesegment x1="6288.49" y1="2981.69" x2="6167.5" y2="2979.98" type="Wall" target=""/>
        </contour>
        <portal target="A0094001_404"/>
        <portal target="A0094001_440"/>
    </space>
    <space name="A0094001_440" type="KAPRUM/LAB">
        <contour>
            <centroid x="5747.91" y="2389.24"/>
            <linesegment x1="5359" y1="2603.6" x2="5359" y2="2198.08" type="Wall" target=""/>
            <linesegment x1="5359" y1="2198.08" x2="5434.37" y2="2198.08" type="Wall" target=""/>
            <linesegment x1="5434.37" y1="2198.08" x2="5654.89" y2="2198.08" type="Window" target=""/>
            <linesegment x1="5654.89" y1="2198.08" x2="5841.83" y2="2198.08" type="Wall" target=""/>
            <linesegment x1="5841.83" y1="2198.08" x2="6060.09" y2="2198.08" type="Window" target=""/>
            <linesegment x1="6060.09" y1="2198.08" x2="6144.61" y2="2198.08" type="Wall" target=""/>
            <linesegment x1="6144.61" y1="2198.08" x2="6144.61" y2="2322.81" type="Wall" target=""/>
            <linesegment x1="6144.61" y1="2322.81" x2="6144.61" y2="2460.83" type="Portal" target="A0094001_439"/>
            <linesegment x1="6144.61" y1="2460.83" x2="6144.61" y2="2604.34" type="Wall" target=""/>
            <linesegment x1="6144.61" y1="2604.34" x2="5926.09" y2="2604.34" type="Wall" target=""/>
            <linesegment x1="5926.09" y1="2604.34" x2="5926.09" y2="2511.3" type="Wall" target=""/>
            <linesegment x1="5926.09" y1="2511.3" x2="5686.09" y2="2511.3" type="Wall" target=""/>
            <linesegment x1="5686.09" y1="2511.3" x2="5686.09" y2="2603.48" type="Wall" target=""/>
            <linesegment x1="5686.09" y1="2603.48" x2="5359" y2="2603.6" type="Wall" target=""/>
        </contour>
        <portal target="A0094001_439"/>
    </space>
    <space name="A0094001_441" type="KONTOR">
        <contour>
            <centroid x="7169.84" y="2589.54"/>
            <linesegment x1="6978.45" y1="2980.72" x2="6978.45" y2="2198.02" type="Wall" target=""/>
            <linesegment x1="6978.45" y1="2198.02" x2="7058.92" y2="2198.02" type="Wall" target=""/>
            <linesegment x1="7058.92" y1="2198.02" x2="7278.17" y2="2198.02" type="Window" target=""/>
            <linesegment x1="7278.17" y1="2198.02" x2="7361.2" y2="2198.02" type="Wall" target=""/>
            <linesegment x1="7361.2" y1="2198.02" x2="7361.2" y2="2981.12" type="Wall" target=""/>
            <linesegment x1="7361.2" y1="2981.12" x2="7238.97" y2="2981.12" type="Wall" target=""/>
            <linesegment x1="7238.97" y1="2981.12" x2="7099.43" y2="2981.12" type="Portal" target="A0094001_404"/>
            <linesegment x1="7099.43" y1="2981.12" x2="6978.45" y2="2980.72" type="Wall" target=""/>
        </contour>
        <portal target="A0094001_404"/>
    </space>
    <space name="A0094001_442" type="KONTOR">
        <contour>
            <centroid x="7573.23" y="2589.1"/>
            <linesegment x1="7382.23" y1="2980.72" x2="7382.23" y2="2196.6" type="Wall" target=""/>
            <linesegment x1="7382.23" y1="2196.6" x2="7462.38" y2="2196.6" type="Wall" target=""/>
            <linesegment x1="7462.38" y1="2196.6" x2="7682.46" y2="2196.6" type="Window" target=""/>
            <linesegment x1="7682.46" y1="2196.6" x2="7764.17" y2="2196.6" type="Wall" target=""/>
            <linesegment x1="7764.17" y1="2196.6" x2="7764.17" y2="2981.76" type="Wall" target=""/>
            <linesegment x1="7764.17" y1="2981.76" x2="7643.55" y2="2981.76" type="Wall" target=""/>
            <linesegment x1="7643.55" y1="2981.76" x2="7505.88" y2="2981.76" type="Portal" target="A0094001_404"/>
            <linesegment x1="7505.88" y1="2981.76" x2="7382.23" y2="2980.72" type="Wall" target=""/>
        </contour>
        <portal target="A0094001_404"/>
    </space>
    <space name="A0094001_443" type="KONTOR">
        <contour>
            <centroid x="7979.9" y="2589.5"/>
            <linesegment x1="7789.57" y1="2979.13" x2="7789.57" y2="2198.39" type="Wall" target=""/>
            <linesegment x1="7789.57" y1="2198.39" x2="7867.93" y2="2198.39" type="Wall" target=""/>
            <linesegment x1="7867.93" y1="2198.39" x2="8087.98" y2="2198.39" type="Window" target=""/>
            <linesegment x1="8087.98" y1="2198.39" x2="8170.13" y2="2198.39" type="Wall" target=""/>
            <linesegment x1="8170.13" y1="2198.39" x2="8170.13" y2="2980.9" type="Wall" target=""/>
            <linesegment x1="8170.13" y1="2980.9" x2="8050.32" y2="2980.9" type="Wall" target=""/>
            <linesegment x1="8050.32" y1="2980.9" x2="7911.19" y2="2980.9" type="Portal" target="A0094001_404"/>
            <linesegment x1="7911.19" y1="2980.9" x2="7789.57" y2="2979.13" type="Wall" target=""/>
        </contour>
        <portal target="A0094001_404"/>
    </space>
    <space name="A0094001_444" type="KONTOR">
        <contour>
            <centroid x="8384.89" y="2588.81"/>
            <linesegment x1="8193.91" y1="2982.61" x2="8193.91" y2="2196.6" type="Wall" target=""/>
            <linesegment x1="8193.91" y1="2196.6" x2="8273.72" y2="2196.6" type="Wall" target=""/>
            <linesegment x1="8273.72" y1="2196.6" x2="8493.14" y2="2196.6" type="Window" target=""/>
            <linesegment x1="8493.14" y1="2196.6" x2="8575.98" y2="2196.6" type="Wall" target=""/>
            <linesegment x1="8575.98" y1="2196.6" x2="8575.98" y2="2980.72" type="Wall" target=""/>
            <linesegment x1="8575.98" y1="2980.72" x2="8453.69" y2="2980.72" type="Wall" target=""/>
            <linesegment x1="8453.69" y1="2980.72" x2="8314.62" y2="2980.72" type="Portal" target="A0094001_404"/>
            <linesegment x1="8314.62" y1="2980.72" x2="8193.91" y2="2982.61" type="Wall" target=""/>
        </contour>
        <portal target="A0094001_404"/>
    </space>
    <space name="A0094001_445" type="TOALETT">
        <contour>
            <centroid x="8826.46" y="2843.59"/>
            <linesegment x1="8616.26" y1="2979.96" x2="8616.26" y2="2707.75" type="Wall" target=""/>
            <linesegment x1="8616.26" y1="2707.75" x2="9041" y2="2707.75" type="Wall" target=""/>
            <linesegment x1="9041" y1="2707.75" x2="9041" y2="2936" type="Wall" target=""/>
            <linesegment x1="9041" y1="2936" x2="9011.26" y2="2936" type="Wall" target=""/>
            <linesegment x1="9011.26" y1="2936" x2="9011.26" y2="2982.49" type="Wall" target=""/>
            <linesegment x1="9011.26" y1="2982.49" x2="8862" y2="2982.49" type="Wall" target=""/>
            <linesegment x1="8862" y1="2982.49" x2="8721.52" y2="2982.49" type="Portal" target="A0094001_404"/>
            <linesegment x1="8721.52" y1="2982.49" x2="8616.26" y2="2979.96" type="Wall" target=""/>
        </contour>
        <portal target="A0094001_404"/>
    </space>
    <space name="A0094001_405" type="KONTOR">
        <contour>
            <centroid x="8791.52" y="3829.41"/>
            <linesegment x1="8601.54" y1="4224.06" x2="8601.54" y2="3434.86" type="Wall" target=""/>
            <linesegment x1="8601.54" y1="3434.86" x2="8719.98" y2="3434.86" type="Wall" target=""/>
            <linesegment x1="8719.98" y1="3434.86" x2="8860.75" y2="3434.86" type="Portal" target="A0094001_404"/>
            <linesegment x1="8860.75" y1="3434.86" x2="8981.5" y2="3434.86" type="Wall" target=""/>
            <linesegment x1="8981.5" y1="3434.86" x2="8981.5" y2="4223.95" type="Wall" target=""/>
            <linesegment x1="8981.5" y1="4223.95" x2="8903.3" y2="4223.95" type="Wall" target=""/>
            <linesegment x1="8903.3" y1="4223.95" x2="8681.57" y2="4223.95" type="Window" target=""/>
            <linesegment x1="8681.57" y1="4223.95" x2="8601.54" y2="4224.06" type="Wall" target=""/>
        </contour>
        <portal target="A0094001_404"/>
    </space>
    <space name="A0094001_406" type="KONTOR">
        <contour>
            <centroid x="8385.63" y="3828.14"/>
            <linesegment x1="8577.39" y1="4221.74" x2="8496.52" y2="4221.74" type="Wall" target=""/>
            <linesegment x1="8496.52" y1="4221.74" x2="8274.78" y2="4221.74" type="Window" target=""/>
            <linesegment x1="8274.78" y1="4221.74" x2="8194.78" y2="4221.74" type="Wall" target=""/>
            <linesegment x1="8194.78" y1="4221.74" x2="8194.78" y2="3433.9" type="Wall" target=""/>
            <linesegment x1="8194.78" y1="3433.9" x2="8313.35" y2="3433.9" type="Wall" target=""/>
            <linesegment x1="8313.35" y1="3433.9" x2="8453.65" y2="3433.9" type="Portal" target="A0094001_404"/>
            <linesegment x1="8453.65" y1="3433.9" x2="8575.55" y2="3433.9" type="Wall" target=""/>
            <linesegment x1="8575.55" y1="3433.9" x2="8577.39" y2="4221.74" type="Wall" target=""/>
        </contour>
        <portal target="A0094001_404"/>
    </space>
    <space name="A0094001_407" type="KONTOR">
        <contour>
            <centroid x="7979.28" y="3829.9"/>
            <linesegment x1="8170.13" y1="4223.06" x2="8090.74" y2="4223.06" type="Wall" target=""/>
            <linesegment x1="8090.74" y1="4223.06" x2="7870.7" y2="4223.06" type="Window" target=""/>
            <linesegment x1="7870.7" y1="4223.06" x2="7788.28" y2="4223.06" type="Wall" target=""/>
            <linesegment x1="7788.28" y1="4223.06" x2="7788.28" y2="3436.84" type="Wall" target=""/>
            <linesegment x1="7788.28" y1="3436.84" x2="7908.61" y2="3436.84" type="Wall" target=""/>
            <linesegment x1="7908.61" y1="3436.84" x2="8049.57" y2="3436.84" type="Portal" target="A0094001_404"/>
            <linesegment x1="8049.57" y1="3436.84" x2="8170.43" y2="3436.84" type="Wall" target=""/>
            <linesegment x1="8170.43" y1="3436.84" x2="8170.13" y2="4223.06" type="Wall" target=""/>
        </contour>
        <portal target="A0094001_404"/>
    </space>
    <space name="A0094001_408" type="KONTOR">
        <contour>
            <centroid x="7574.55" y="3830.15"/>
            <linesegment x1="7382" y1="4222" x2="7382" y2="3436.52" type="Wall" target=""/>
            <linesegment x1="7382" y1="3436.52" x2="7503.48" y2="3436.52" type="Wall" target=""/>
            <linesegment x1="7503.48" y1="3436.52" x2="7642" y2="3436.52" type="Portal" target="A0094001_404"/>
            <linesegment x1="7642" y1="3436.52" x2="7767" y2="3436.52" type="Wall" target=""/>
            <linesegment x1="7767" y1="3436.52" x2="7767" y2="4224" type="Wall" target=""/>
            <linesegment x1="7767" y1="4224" x2="7684" y2="4224" type="Wall" target=""/>
            <linesegment x1="7684" y1="4224" x2="7465" y2="4224" type="Window" target=""/>
            <linesegment x1="7465" y1="4224" x2="7382" y2="4222" type="Wall" target=""/>
        </contour>
        <portal target="A0094001_404"/>
    </space>
    <space name="A0094001_409" type="KONTOR">
        <contour>
            <centroid x="7170.09" y="3828.77"/>
            <linesegment x1="7361.06" y1="4222.31" x2="7281.66" y2="4222.31" type="Wall" target=""/>
            <linesegment x1="7281.66" y1="4222.31" x2="7055.58" y2="4222.31" type="Window" target=""/>
            <linesegment x1="7055.58" y1="4222.31" x2="6979.21" y2="4222.31" type="Wall" target=""/>
            <linesegment x1="6979.21" y1="4222.31" x2="6979.21" y2="3435.16" type="Wall" target=""/>
            <linesegment x1="6979.21" y1="3435.16" x2="7097.92" y2="3435.16" type="Wall" target=""/>
            <linesegment x1="7097.92" y1="3435.16" x2="7235.65" y2="3435.16" type="Portal" target="A0094001_404"/>
            <linesegment x1="7235.65" y1="3435.16" x2="7360.87" y2="3435.16" type="Wall" target=""/>
            <linesegment x1="7360.87" y1="3435.16" x2="7361.06" y2="4222.31" type="Wall" target=""/>
        </contour>
        <portal target="A0094001_404"/>
    </space>
    <space name="A0094001_410" type="KONTOR">
        <contour>
            <centroid x="6761.7" y="3828.33"/>
            <linesegment x1="6952.9" y1="4221.65" x2="6873.04" y2="4221.65" type="Wall" target=""/>
            <linesegment x1="6873.04" y1="4221.65" x2="6652.17" y2="4221.65" type="Window" target=""/>
            <linesegment x1="6652.17" y1="4221.65" x2="6569.57" y2="4221.65" type="Wall" target=""/>
            <linesegment x1="6569.57" y1="4221.65" x2="6569.57" y2="3435.65" type="Wall" target=""/>
            <linesegment x1="6569.57" y1="3435.65" x2="6692.17" y2="3435.65" type="Wall" target=""/>
            <linesegment x1="6692.17" y1="3435.65" x2="6830.71" y2="3435.65" type="Portal" target="A0094001_404"/>
            <linesegment x1="6830.71" y1="3435.65" x2="6954.78" y2="3435.65" type="Wall" target=""/>
            <linesegment x1="6954.78" y1="3435.65" x2="6952.9" y2="4221.65" type="Wall" target=""/>
        </contour>
        <portal target="A0094001_404"/>
    </space>
    <space name="A0094001_412" type="KONTOR">
        <contour>
            <centroid x="6323.59" y="3828.92"/>
            <linesegment x1="6099" y1="4222" x2="6099" y2="3435" type="Wall" target=""/>
            <linesegment x1="6099" y1="3435" x2="6286" y2="3435" type="Wall" target=""/>
            <linesegment x1="6286" y1="3435" x2="6426.2" y2="3435" type="Portal" target="A0094001_404"/>
            <linesegment x1="6426.2" y1="3435" x2="6548.1" y2="3435" type="Wall" target=""/>
            <linesegment x1="6548.1" y1="3435" x2="6548.1" y2="4223" type="Wall" target=""/>
            <linesegment x1="6548.1" y1="4223" x2="6470" y2="4223" type="Wall" target=""/>
            <linesegment x1="6470" y1="4223" x2="6249" y2="4223" type="Window" target=""/>
            <linesegment x1="6249" y1="4223" x2="6099" y2="4222" type="Wall" target=""/>
        </contour>
        <portal target="A0094001_404"/>
    </space>
    <space name="A0094001_411" type="ATEM.PREP. LAB">
        <contour>
            <centroid x="5731.85" y="3867.45"/>
            <linesegment x1="5356.52" y1="4220.87" x2="5356.52" y2="3773.57" type="Wall" target=""/>
            <linesegment x1="5356.52" y1="3773.57" x2="5414.5" y2="3773.57" type="Wall" target=""/>
            <linesegment x1="5414.5" y1="3773.57" x2="5414.5" y2="3687.24" type="Wall" target=""/>
            <linesegment x1="5414.5" y1="3687.24" x2="5356.18" y2="3687.24" type="Wall" target=""/>
            <linesegment x1="5356.18" y1="3687.24" x2="5356.18" y2="3551.73" type="Wall" target=""/>
            <linesegment x1="5356.18" y1="3551.73" x2="5837.03" y2="3551.73" type="Wall" target=""/>
            <linesegment x1="5837.03" y1="3551.73" x2="5837.03" y2="3437.95" type="Wall" target=""/>
            <linesegment x1="5837.03" y1="3437.95" x2="5880.48" y2="3437.95" type="Wall" target=""/>
            <linesegment x1="5880.48" y1="3437.95" x2="6019.56" y2="3437.95" type="Portal" target="A0094001_404"/>
            <linesegment x1="6019.56" y1="3437.95" x2="6074.79" y2="3437.95" type="Wall" target=""/>
            <linesegment x1="6074.79" y1="3437.95" x2="6074.79" y2="4222.31" type="Wall" target=""/>
            <linesegment x1="6074.79" y1="4222.31" x2="6064.27" y2="4222.31" type="Wall" target=""/>
            <linesegment x1="6064.27" y1="4222.31" x2="5842.72" y2="4222.31" type="Window" target=""/>
            <linesegment x1="5842.72" y1="4222.31" x2="5656.71" y2="4222.31" type="Wall" target=""/>
            <linesegment x1="5656.71" y1="4222.31" x2="5436.67" y2="4222.31" type="Window" target=""/>
            <linesegment x1="5436.67" y1="4222.31" x2="5356.52" y2="4220.87" type="Wall" target=""/>
        </contour>
        <portal target="A0094001_404"/>
    </space>
    <space name="A0094001_TRH1" type="TRAPPA">
        <contour>
            <centroid x="9648.49" y="2795.91"/>
            <linesegment x1="9088.7" y1="3389.57" x2="9088.7" y2="3109.6" type="Portal" target="A0094001_404"/>
            <linesegment x1="9088.7" y1="3109.6" x2="9088.7" y2="2645" type="Wall" target=""/>
            <linesegment x1="9088.7" y1="2645" x2="9088.7" y2="2536.11" type="Portal" target="A0094001_446"/>
            <linesegment x1="9088.7" y1="2536.11" x2="9088.7" y2="2446.88" type="Wall" target=""/>
            <linesegment x1="9088.7" y1="2446.88" x2="9088.7" y2="2320.7" type="Portal" target="A0094001_447"/>
            <linesegment x1="9088.7" y1="2320.7" x2="9088.7" y2="2195.35" type="Wall" target=""/>
            <linesegment x1="9088.7" y1="2195.35" x2="9324.2" y2="2195.35" type="Wall" target=""/>
            <linesegment x1="9324.2" y1="2195.35" x2="9461.63" y2="2195.35" type="Portal" target="A0094001_448"/>
            <linesegment x1="9461.63" y1="2195.35" x2="10199.6" y2="2195.35" type="Wall" target=""/>
            <linesegment x1="10199.6" y1="2195.35" x2="10199.6" y2="3109.57" type="Wall" target=""/>
            <linesegment x1="10199.6" y1="3109.57" x2="10235.7" y2="3109.57" type="Wall" target=""/>
            <linesegment x1="10235.7" y1="3109.57" x2="10235.7" y2="3389.57" type="Window" target=""/>
            <linesegment x1="10235.7" y1="3389.57" x2="10069.6" y2="3389.57" type="Wall" target=""/>
            <linesegment x1="10069.6" y1="3389.57" x2="9947.07" y2="3389.57" type="Portal" target="A0094001_401"/>
            <linesegment x1="9947.07" y1="3389.57" x2="9664.27" y2="3389.57" type="Wall" target=""/>
            <linesegment x1="9664.27" y1="3389.57" x2="9539.9" y2="3389.57" type="Portal" target="A0094001_402"/>
            <linesegment x1="9539.9" y1="3389.57" x2="9257.83" y2="3389.57" type="Wall" target=""/>
            <linesegment x1="9257.83" y1="3389.57" x2="9134.97" y2="3389.57" type="Portal" target="A0094001_403"/>
            <linesegment x1="9134.97" y1="3389.57" x2="9088.7" y2="3389.57" type="Wall" target=""/>
        </contour>
        <portal target="A0094001_404"/>
        <portal target="A0094001_403"/>
        <portal target="A0094001_402"/>
        <portal target="A0094001_401"/>
        <portal target="A0094001_000"/>
        <portal target="A0094001_446"/>
        <portal target="A0094001_447"/>
        <portal target="A0094001_448"/>
    </space>
    <space name="A0094001_403" type="KONTOR">
        <contour>
            <centroid x="9197.25" y="3827.81"/>
            <linesegment x1="9004.5" y1="4221.65" x2="9004.5" y2="3433.9" type="Wall" target=""/>
            <linesegment x1="9004.5" y1="3433.9" x2="9126.65" y2="3433.9" type="Wall" target=""/>
            <linesegment x1="9126.65" y1="3433.9" x2="9266" y2="3433.9" type="Portal" target="A0094001_TRH1"/>
            <linesegment x1="9266" y1="3433.9" x2="9390" y2="3433.9" type="Wall" target=""/>
            <linesegment x1="9390" y1="3433.9" x2="9390" y2="4221.74" type="Wall" target=""/>
            <linesegment x1="9390" y1="4221.74" x2="9304.35" y2="4221.74" type="Wall" target=""/>
            <linesegment x1="9304.35" y1="4221.74" x2="9086.96" y2="4221.74" type="Window" target=""/>
            <linesegment x1="9086.96" y1="4221.74" x2="9004.5" y2="4221.65" type="Wall" target=""/>
        </contour>
        <portal target="A0094001_TRH1"/>
    </space>
    <space name="A0094001_402" type="KONTOR">
        <contour>
            <centroid x="9602.4" y="3828.63"/>
            <linesegment x1="9792.39" y1="4221.91" x2="9712.83" y2="4221.91" type="Wall" target=""/>
            <linesegment x1="9712.83" y1="4221.91" x2="9492.25" y2="4221.91" type="Window" target=""/>
            <linesegment x1="9492.25" y1="4221.91" x2="9412.2" y2="4221.91" type="Wall" target=""/>
            <linesegment x1="9412.2" y1="4221.91" x2="9412.2" y2="3435.49" type="Wall" target=""/>
            <linesegment x1="9412.2" y1="3435.49" x2="9530.38" y2="3435.49" type="Wall" target=""/>
            <linesegment x1="9530.38" y1="3435.49" x2="9669.57" y2="3435.49" type="Portal" target="A0094001_TRH1"/>
            <linesegment x1="9669.57" y1="3435.49" x2="9792.82" y2="3435.49" type="Wall" target=""/>
            <linesegment x1="9792.82" y1="3435.49" x2="9792.39" y2="4221.91" type="Wall" target=""/>
        </contour>
        <portal target="A0094001_TRH1"/>
    </space>
    <space name="A0094001_401" type="KONTOR">
        <contour>
            <centroid x="10007.5" y="3831.84"/>
            <linesegment x1="9817" y1="4220" x2="9817" y2="3436.49" type="Wall" target=""/>
            <linesegment x1="9817" y1="3436.49" x2="9936.57" y2="3436.49" type="Wall" target=""/>
            <linesegment x1="9936.57" y1="3436.49" x2="10074" y2="3436.49" type="Portal" target="A0094001_TRH1"/>
            <linesegment x1="10074" y1="3436.49" x2="10151" y2="3436.49" type="Wall" target=""/>
            <linesegment x1="10151" y1="3436.49" x2="10151" y2="3483.35" type="Wall" target=""/>
            <linesegment x1="10151" y1="3483.35" x2="10200.5" y2="3483.35" type="Wall" target=""/>
            <linesegment x1="10200.5" y1="3483.35" x2="10200.5" y2="4221.65" type="Wall" target=""/>
            <linesegment x1="10200.5" y1="4221.65" x2="10117.4" y2="4221.65" type="Wall" target=""/>
            <linesegment x1="10117.4" y1="4221.65" x2="9898.26" y2="4221.65" type="Window" target=""/>
            <linesegment x1="9898.26" y1="4221.65" x2="9817" y2="4220" type="Wall" target=""/>
        </contour>
        <portal target="A0094001_TRH1"/>
    </space>
    <space name="A0094001_000" type="HISS">
        <contour>
            <centroid x="9742.32" y="2577.53"/>
            <linesegment x1="9554.37" y1="2691.87" x2="9554.37" y2="2649.13" type="Wall" target=""/>
            <linesegment x1="9554.37" y1="2649.13" x2="9554.37" y2="2509.57" type="Portal" target="A0094001_TRH1"/>
            <linesegment x1="9554.37" y1="2509.57" x2="9554.37" y2="2463.48" type="Wall" target=""/>
            <linesegment x1="9554.37" y1="2463.48" x2="9930.43" y2="2463.48" type="Wall" target=""/>
            <linesegment x1="9930.43" y1="2463.48" x2="9930.43" y2="2691.3" type="Wall" target=""/>
            <linesegment x1="9930.43" y1="2691.3" x2="9554.37" y2="2691.87" type="Wall" target=""/>
        </contour>
        <portal target="A0094001_TRH1"/>
    </space>
    <space name="A0094001_446" type="TOALETT">
        <contour>
            <centroid x="8928.75" y="2604.18"/>
            <linesegment x1="8809.07" y1="2688.09" x2="8809.07" y2="2520.98" type="Wall" target=""/>
            <linesegment x1="8809.07" y1="2520.98" x2="9048.77" y2="2520.98" type="Wall" target=""/>
            <linesegment x1="9048.77" y1="2520.98" x2="9048.77" y2="2647.79" type="Portal" target="A0094001_TRH1"/>
            <linesegment x1="9048.77" y1="2647.79" x2="9048.77" y2="2686.67" type="Wall" target=""/>
            <linesegment x1="9048.77" y1="2686.67" x2="8809.07" y2="2688.09" type="Wall" target=""/>
        </contour>
        <portal target="A0094001_TRH1"/>
    </space>
    <space name="A0094001_447" type="">
        <contour>
            <centroid x="8807.38" y="2395.13"/>
            <linesegment x1="8618.26" y1="2688.7" x2="8618.26" y2="2194.78" type="Wall" target=""/>
            <linesegment x1="8618.26" y1="2194.78" x2="8679.13" y2="2194.78" type="Wall" target=""/>
            <linesegment x1="8679.13" y1="2194.78" x2="8899.05" y2="2194.78" type="Window" target=""/>
            <linesegment x1="8899.05" y1="2194.78" x2="9047.26" y2="2194.78" type="Wall" target=""/>
            <linesegment x1="9047.26" y1="2194.78" x2="9047.26" y2="2317.58" type="Wall" target=""/>
            <linesegment x1="9047.26" y1="2317.58" x2="9047.26" y2="2451" type="Portal" target="A0094001_TRH1"/>
            <linesegment x1="9047.26" y1="2451" x2="9047.26" y2="2500" type="Wall" target=""/>
            <linesegment x1="9047.26" y1="2500" x2="8785" y2="2500" type="Wall" target=""/>
            <linesegment x1="8785" y1="2500" x2="8785" y2="2688" type="Wall" target=""/>
            <linesegment x1="8785" y1="2688" x2="8618.26" y2="2688.7" type="Wall" target=""/>
        </contour>
        <portal target="A0094001_TRH1"/>
    </space>
    <space name="A0094001_448" type="FLÄKTRUM">
        <contour>
            <centroid x="10858.8" y="1884.16"/>
            <linesegment x1="9090" y1="2132" x2="9090" y2="2051" type="Wall" target=""/>
            <linesegment x1="9090" y1="2051" x2="9090" y2="1769.38" type="Window" target=""/>
            <linesegment x1="9090" y1="1769.38" x2="9090" y2="1272.59" type="Wall" target=""/>
            <linesegment x1="9090" y1="1272.59" x2="12310.7" y2="1272.59" type="Wall" target=""/>
            <linesegment x1="12310.7" y1="1272.59" x2="12310.7" y2="2628.76" type="Wall" target=""/>
            <linesegment x1="12310.7" y1="2628.76" x2="10266.7" y2="2628.76" type="Wall" target=""/>
            <linesegment x1="10266.7" y1="2628.76" x2="10266.7" y2="2130.29" type="Wall" target=""/>
            <linesegment x1="10266.7" y1="2130.29" x2="9470.43" y2="2130.29" type="Wall" target=""/>
            <linesegment x1="9470.43" y1="2130.29" x2="9274.75" y2="2130.29" type="Portal" target="A0094001_TRH1"/>
            <linesegment x1="9274.75" y1="2130.29" x2="9090" y2="2132" type="Wall" target=""/>
        </contour>
        <portal target="A0094001_TRH1"/>
    </space>
</floor>
